proactuary/__init__.py
proactuary/_proactuary.py
proactuary/_util.py
proactuary/py.typed
proactuary/version.py
proactuary-0.1.2.dist-info/LICENSE
proactuary-0.1.2.dist-info/METADATA
proactuary-0.1.2.dist-info/WHEEL
proactuary-0.1.2.dist-info/top_level.txt
proactuary-0.1.2.dist-info/RECORD
