Metadata-Version: 2.1
Name: proactuary
Version: 0.1.2
Summary: ProActuary: Package to read and operate on actuarial file formats
Author: Auto Actuary
Project-URL: repository, https://github.com/autoactuary/proactuary
Classifier: Programming Language :: Python :: 3
Classifier: License :: OSI Approved :: MIT License
Classifier: Operating System :: OS Independent
Requires-Python: >=3.6
License-File: LICENSE
Requires-Dist: pandas >=1.0.0
